{
  "capacityMeshNodeId": "cmn_222",
  "center": {
    "x": 12.399999999999999,
    "y": 20.625
  },
  "width": 1.5,
  "height": 1.5,
  "portPoints": [
    {
      "portPointId": "ce85_pp1_z0::0",
      "x": 12.224999999999998,
      "y": 19.875,
      "z": 0,
      "connectionName": "source_net_22",
      "rootConnectionName": "source_net_22"
    },
    {
      "portPointId": "tiny-terminal:end-port:source_net_22",
      "x": 12.399999999999999,
      "y": 20.625,
      "z": 0,
      "connectionName": "source_net_22",
      "rootConnectionName": "source_net_22"
    }
  ],
  "availableZ": [
    0,
    1
  ]
}
