{
  "capacityMeshNodeId": "cmn_81",
  "center": {
    "x": 8.27,
    "y": 5.35
  },
  "width": 0.6699999999999999,
  "height": 1,
  "portPoints": [
    {
      "portPointId": "ce509_pp1_z0::0",
      "x": 8.604999999999999,
      "y": 5.625,
      "z": 0,
      "connectionName": "source_net_14",
      "rootConnectionName": "source_net_14"
    },
    {
      "portPointId": "ce155_pp0_z0::0",
      "x": 8.255,
      "y": 4.85,
      "z": 0,
      "connectionName": "source_net_14",
      "rootConnectionName": "source_net_14"
    }
  ],
  "availableZ": [
    0
  ]
}
