{
  "capacityMeshNodeId": "cmn_138",
  "center": {
    "x": 4.824999999999999,
    "y": -5
  },
  "width": 0.7999999999999998,
  "height": 0.9500000000000002,
  "portPoints": [
    {
      "portPointId": "ce41_pp1_z1::1",
      "x": 5,
      "y": -5.475,
      "z": 1,
      "connectionName": "source_net_5_mst0",
      "rootConnectionName": "source_net_5"
    },
    {
      "portPointId": "tiny-terminal:end-port:source_net_5_mst0",
      "x": 4.825,
      "y": -5,
      "z": 1,
      "connectionName": "source_net_5_mst0",
      "rootConnectionName": "source_net_5"
    },
    {
      "portPointId": "ce52_pp0_z1::1",
      "x": 5.2250000000000005,
      "y": -5.25,
      "z": 1,
      "connectionName": "source_net_5_mst1",
      "rootConnectionName": "source_net_5"
    },
    {
      "portPointId": "tiny-terminal:end-port:source_net_5_mst1",
      "x": 4.825,
      "y": -5,
      "z": 1,
      "connectionName": "source_net_5_mst1",
      "rootConnectionName": "source_net_5"
    }
  ],
  "availableZ": [
    1
  ]
}
