{
  "capacityMeshNodeId": "cmn_12",
  "center": {
    "x": 26.909999999999997,
    "y": 11.25
  },
  "width": 14.620000000000005,
  "height": 8.5,
  "portPoints": [
    {
      "portPointId": "ce288_pp0_z0::0",
      "x": 30.04,
      "y": 15.5,
      "z": 0,
      "connectionName": "source_net_32",
      "rootConnectionName": "source_net_32"
    },
    {
      "portPointId": "ce275_pp0_z1::1",
      "x": 19.599999999999994,
      "y": 7.2496874999999985,
      "z": 1,
      "connectionName": "source_net_32",
      "rootConnectionName": "source_net_32"
    },
    {
      "portPointId": "ce280_pp3_z0::0",
      "x": 24.214999999999996,
      "y": 15.5,
      "z": 0,
      "connectionName": "source_net_31",
      "rootConnectionName": "source_net_31"
    },
    {
      "portPointId": "ce290_pp4_z0::0",
      "x": 32.65109375000001,
      "y": 7,
      "z": 0,
      "connectionName": "source_net_31",
      "rootConnectionName": "source_net_31"
    },
    {
      "portPointId": "ce285_pp3_z1::1",
      "x": 29.574062500000004,
      "y": 7,
      "z": 1,
      "connectionName": "source_net_28",
      "rootConnectionName": "source_net_28"
    },
    {
      "portPointId": "ce287_pp1_z1::1",
      "x": 28.595,
      "y": 15.5,
      "z": 1,
      "connectionName": "source_net_28",
      "rootConnectionName": "source_net_28"
    },
    {
      "portPointId": "ce285_pp8_z0::0",
      "x": 29.574062500000004,
      "y": 7,
      "z": 0,
      "connectionName": "source_net_20_mst0",
      "rootConnectionName": "source_net_20"
    },
    {
      "portPointId": "ce294_pp0_z0::0",
      "x": 34.22,
      "y": 11.25,
      "z": 0,
      "connectionName": "source_net_20_mst0",
      "rootConnectionName": "source_net_20"
    },
    {
      "portPointId": "ce275_pp1_z1::1",
      "x": 19.599999999999994,
      "y": 7.749062499999997,
      "z": 1,
      "connectionName": "source_net_20_mst2",
      "rootConnectionName": "source_net_20"
    },
    {
      "portPointId": "ce283_pp1_z1::1",
      "x": 26.095,
      "y": 7,
      "z": 1,
      "connectionName": "source_net_20_mst2",
      "rootConnectionName": "source_net_20"
    },
    {
      "portPointId": "ce295_pp0_z1::1",
      "x": 34.22,
      "y": 11.25,
      "z": 1,
      "connectionName": "source_net_19",
      "rootConnectionName": "source_net_19"
    },
    {
      "portPointId": "ce272_pp7_z1::1",
      "x": 19.599999999999994,
      "y": 13.3984375,
      "z": 1,
      "connectionName": "source_net_19",
      "rootConnectionName": "source_net_19"
    },
    {
      "portPointId": "ce272_pp7_z0::0",
      "x": 19.599999999999994,
      "y": 13.3984375,
      "z": 0,
      "connectionName": "source_net_18_mst1",
      "rootConnectionName": "source_net_18"
    },
    {
      "portPointId": "ce284_pp1_z0::0",
      "x": 26.055,
      "y": 15.5,
      "z": 0,
      "connectionName": "source_net_18_mst1",
      "rootConnectionName": "source_net_18"
    },
    {
      "portPointId": "ce273_pp0_z0::0",
      "x": 21.29,
      "y": 7,
      "z": 0,
      "connectionName": "source_net_13_mst0",
      "rootConnectionName": "source_net_13"
    },
    {
      "portPointId": "ce270_pp1_z0::0",
      "x": 19.599999999999994,
      "y": 8.75,
      "z": 0,
      "connectionName": "source_net_13_mst0",
      "rootConnectionName": "source_net_13"
    },
    {
      "portPointId": "ce290_pp5_z0::0",
      "x": 33.69703125,
      "y": 7,
      "z": 0,
      "connectionName": "source_net_12_mst1",
      "rootConnectionName": "source_net_12"
    },
    {
      "portPointId": "ce292_pp2_z0::0",
      "x": 33.995,
      "y": 15.5,
      "z": 0,
      "connectionName": "source_net_12_mst1",
      "rootConnectionName": "source_net_12"
    }
  ],
  "availableZ": [
    0,
    1
  ]
}
