{
  "capacityMeshNodeId": "cmn_123",
  "center": {
    "x": -5.5375,
    "y": -4.8475
  },
  "width": 1.2249999999999988,
  "height": 1.0949999999999998,
  "portPoints": [
    {
      "portPointId": "ce8_pp1_z0::0",
      "x": -5.5375,
      "y": -4.300000000000001,
      "z": 0,
      "connectionName": "source_net_17",
      "rootConnectionName": "source_net_17"
    },
    {
      "portPointId": "ce698_pp0_z0::0",
      "x": -5.924999999999999,
      "y": -5.395,
      "z": 0,
      "connectionName": "source_net_17",
      "rootConnectionName": "source_net_17"
    }
  ],
  "availableZ": [
    0
  ]
}
