{
  "capacityMeshNodeId": "cmn_309",
  "center": {
    "x": -31.810000000000002,
    "y": -5
  },
  "width": 1.5,
  "height": 1.5,
  "portPoints": [
    {
      "portPointId": "tiny-terminal:start-port:source_net_4_mst0",
      "x": -31.81,
      "y": -5,
      "z": 0,
      "connectionName": "source_net_4_mst0",
      "rootConnectionName": "source_net_4"
    },
    {
      "portPointId": "ce823_pp3_z0::0",
      "x": -31.060000000000002,
      "y": -4.475,
      "z": 0,
      "connectionName": "source_net_4_mst0",
      "rootConnectionName": "source_net_4"
    }
  ],
  "availableZ": [
    0,
    1
  ]
}
