{
  "capacityMeshNodeId": "cmn_136",
  "center": {
    "x": -15.070710678118655,
    "y": -2.914213562373095
  },
  "width": 0.5500000000000007,
  "height": 0.8485281374238571,
  "portPoints": [
    {
      "portPointId": "ce509_pp0_z0::0",
      "x": -14.97248737341529,
      "y": -3.3384776310850235,
      "z": 0,
      "connectionName": "source_net_5",
      "rootConnectionName": "source_net_5"
    },
    {
      "portPointId": "tiny-terminal:end-port:source_net_5",
      "x": -15.247487373415291,
      "y": -3.090990257669732,
      "z": 0,
      "connectionName": "source_net_5",
      "rootConnectionName": "source_net_5"
    }
  ],
  "availableZ": [
    0
  ]
}
