{
  "capacityMeshNodeId": "cmn_50",
  "center": {
    "x": -4,
    "y": -6.329999999999999
  },
  "width": 1.5599999999999992,
  "height": 2.700000000000003,
  "portPoints": [
    {
      "portPointId": "ce488_pp0_z0::0",
      "x": -4.39,
      "y": -4.979999999999998,
      "z": 0,
      "connectionName": "source_net_9_mst2",
      "rootConnectionName": "source_net_9"
    },
    {
      "portPointId": "ce595_pp0_z0::0",
      "x": -4.51,
      "y": -7.68,
      "z": 0,
      "connectionName": "source_net_9_mst2",
      "rootConnectionName": "source_net_9"
    },
    {
      "portPointId": "ce597_pp0_z0::0",
      "x": -3.49,
      "y": -7.68,
      "z": 0,
      "connectionName": "source_net_0_mst1",
      "rootConnectionName": "source_net_0"
    },
    {
      "portPointId": "ce488_pp3_z0::0",
      "x": -3.6100000000000003,
      "y": -4.979999999999998,
      "z": 0,
      "connectionName": "source_net_0_mst1",
      "rootConnectionName": "source_net_0"
    }
  ],
  "availableZ": [
    0,
    1
  ]
}
