{
  "capacityMeshNodeId": "cmn_0",
  "center": {
    "x": -6.7785000000000055,
    "y": -11.440000000000001
  },
  "width": 15.089999999999998,
  "height": 5.029999999999999,
  "portPoints": [
    {
      "portPointId": "ce1_pp6_z1::1",
      "x": -11.527125,
      "y": -8.925,
      "z": 1,
      "connectionName": "source_net_14_mst0",
      "rootConnectionName": "source_net_14"
    },
    {
      "portPointId": "ce17_pp5_z1::1",
      "x": -0.7489999999999783,
      "y": -13.955000000000002,
      "z": 1,
      "connectionName": "source_net_14_mst0",
      "rootConnectionName": "source_net_14"
    },
    {
      "portPointId": "ce1_pp6_z0::0",
      "x": -12.45925,
      "y": -8.925,
      "z": 0,
      "connectionName": "source_net_10_mst1",
      "rootConnectionName": "source_net_10"
    },
    {
      "portPointId": "ce12_pp10_z0::0",
      "x": -6.294124999999977,
      "y": -13.955000000000002,
      "z": 0,
      "connectionName": "source_net_10_mst1",
      "rootConnectionName": "source_net_10"
    },
    {
      "portPointId": "ce6_pp4_z0::0",
      "x": -13.431750000000001,
      "y": -13.955000000000002,
      "z": 0,
      "connectionName": "source_net_4_mst2",
      "rootConnectionName": "source_net_4"
    },
    {
      "portPointId": "ce18_pp4_z0::0",
      "x": 0.7664999999999935,
      "y": -11.440000000000001,
      "z": 0,
      "connectionName": "source_net_4_mst2",
      "rootConnectionName": "source_net_4"
    },
    {
      "portPointId": "ce1_pp4_z1::1",
      "x": -13.391375000000004,
      "y": -8.925,
      "z": 1,
      "connectionName": "source_net_0",
      "rootConnectionName": "source_net_0"
    },
    {
      "portPointId": "ce7_pp1_z1::1",
      "x": -11.9775,
      "y": -13.955000000000002,
      "z": 1,
      "connectionName": "source_net_0",
      "rootConnectionName": "source_net_0"
    }
  ],
  "availableZ": [
    0,
    1,
    2,
    3
  ]
}
