{
  "capacityMeshNodeId": "cmn_213",
  "center": {
    "x": -15.75,
    "y": 15.810000000000002
  },
  "width": 1.5,
  "height": 1.5000000000000018,
  "portPoints": [
    {
      "portPointId": "ce915_pp1_z0::0",
      "x": -15.925,
      "y": 15.060000000000002,
      "z": 0,
      "connectionName": "source_net_9_mst0",
      "rootConnectionName": "source_net_9"
    },
    {
      "portPointId": "tiny-terminal:end-port:source_net_9_mst0",
      "x": -15.75,
      "y": 15.81,
      "z": 0,
      "connectionName": "source_net_9_mst0",
      "rootConnectionName": "source_net_9"
    }
  ],
  "availableZ": [
    0,
    1,
    2,
    3
  ]
}
