{
  "capacityMeshNodeId": "new-cmn_3-13",
  "center": {
    "x": -11.9875,
    "y": -13.48
  },
  "width": 0.14500000000000135,
  "height": 4.799999999999999,
  "portPoints": [
    {
      "portPointId": "ce106_pp2_z3::3",
      "x": -11.915,
      "y": -14.68,
      "z": 3,
      "connectionName": "source_net_10_mst0",
      "rootConnectionName": "source_net_10"
    },
    {
      "portPointId": "ce745_pp0_z3_cramped::3",
      "x": -12.060000000000002,
      "y": -15.48,
      "z": 3,
      "connectionName": "source_net_10_mst0",
      "rootConnectionName": "source_net_10"
    },
    {
      "portPointId": "ce710_pp0_z3::3",
      "x": -12.060000000000002,
      "y": -15.23,
      "z": 3,
      "connectionName": "source_net_10_mst1",
      "rootConnectionName": "source_net_10"
    },
    {
      "portPointId": "ce106_pp4_z3::3",
      "x": -11.915,
      "y": -13.88,
      "z": 3,
      "connectionName": "source_net_10_mst1",
      "rootConnectionName": "source_net_10"
    },
    {
      "portPointId": "ce747_pp0_z3_cramped::3",
      "x": -12.060000000000002,
      "y": -14.48,
      "z": 3,
      "connectionName": "source_net_9",
      "rootConnectionName": "source_net_9"
    },
    {
      "portPointId": "ce748_pp0_z3_cramped::3",
      "x": -12.060000000000002,
      "y": -13.98,
      "z": 3,
      "connectionName": "source_net_9",
      "rootConnectionName": "source_net_9"
    },
    {
      "portPointId": "ce749_pp0_z3_cramped::3",
      "x": -12.060000000000002,
      "y": -13.48,
      "z": 3,
      "connectionName": "source_net_7_mst1",
      "rootConnectionName": "source_net_7"
    },
    {
      "portPointId": "ce106_pp6_z3::3",
      "x": -11.915,
      "y": -12.280000000000001,
      "z": 3,
      "connectionName": "source_net_7_mst1",
      "rootConnectionName": "source_net_7"
    },
    {
      "portPointId": "ce693_pp0_z3::3",
      "x": -12.060000000000002,
      "y": -12.23,
      "z": 3,
      "connectionName": "source_net_6_mst2",
      "rootConnectionName": "source_net_6"
    },
    {
      "portPointId": "ce106_pp7_z3::3",
      "x": -11.915,
      "y": -11.480000000000002,
      "z": 3,
      "connectionName": "source_net_6_mst2",
      "rootConnectionName": "source_net_6"
    },
    {
      "portPointId": "ce753_pp0_z3_cramped::3",
      "x": -12.060000000000002,
      "y": -11.48,
      "z": 3,
      "connectionName": "source_net_3",
      "rootConnectionName": "source_net_3"
    },
    {
      "portPointId": "ce143_pp0_z3_cramped::3",
      "x": -11.9875,
      "y": -11.080000000000002,
      "z": 3,
      "connectionName": "source_net_3",
      "rootConnectionName": "source_net_3"
    },
    {
      "portPointId": "ce711_pp0_z3::3",
      "x": -12.060000000000002,
      "y": -15.73,
      "z": 3,
      "connectionName": "source_net_2_mst0",
      "rootConnectionName": "source_net_2"
    },
    {
      "portPointId": "ce106_pp1_z3::3",
      "x": -11.915,
      "y": -15.479999999999999,
      "z": 3,
      "connectionName": "source_net_2_mst0",
      "rootConnectionName": "source_net_2"
    },
    {
      "portPointId": "ce746_pp0_z3_cramped::3",
      "x": -12.060000000000002,
      "y": -14.98,
      "z": 3,
      "connectionName": "source_net_0_mst1",
      "rootConnectionName": "source_net_0"
    },
    {
      "portPointId": "ce106_pp5_z3::3",
      "x": -11.915,
      "y": -13.08,
      "z": 3,
      "connectionName": "source_net_0_mst1",
      "rootConnectionName": "source_net_0"
    }
  ],
  "availableZ": [
    3
  ]
}
