{
  "capacityMeshNodeId": "cmn_72",
  "center": {
    "x": -2.2475000000000005,
    "y": -3.8499999999999996
  },
  "width": 1.685,
  "height": 1.75,
  "portPoints": [
    {
      "portPointId": "ce62_pp2_z3::3",
      "x": -1.4050000000000002,
      "y": -3.8499999999999996,
      "z": 3,
      "connectionName": "source_net_20",
      "rootConnectionName": "source_net_20"
    },
    {
      "portPointId": "ce539_pp2_z3::3",
      "x": -3.0900000000000003,
      "y": -3.8499999999999996,
      "z": 3,
      "connectionName": "source_net_20",
      "rootConnectionName": "source_net_20"
    }
  ],
  "availableZ": [
    3
  ]
}
