{
  "capacityMeshNodeId": "cmn_60",
  "center": {
    "x": 8.325,
    "y": 1.2500000000000002
  },
  "width": 0.8000000000000007,
  "height": 0.9499999999999997,
  "portPoints": [
    {
      "portPointId": "ce93_pp1_z1::1",
      "x": 8.5,
      "y": 0.7750000000000004,
      "z": 1,
      "connectionName": "source_net_0_mst2",
      "rootConnectionName": "source_net_0"
    },
    {
      "portPointId": "ce507_pp0_z1::1",
      "x": 8.724999999999998,
      "y": 1.0000000000000004,
      "z": 1,
      "connectionName": "source_net_0_mst2",
      "rootConnectionName": "source_net_0"
    },
    {
      "portPointId": "ce505_pp0_z1::1",
      "x": 7.924999999999999,
      "y": 1.0000000000000004,
      "z": 1,
      "connectionName": "source_net_5_mst1",
      "rootConnectionName": "source_net_5"
    },
    {
      "portPointId": "ce93_pp0_z1::1",
      "x": 8.149999999999999,
      "y": 0.7750000000000004,
      "z": 1,
      "connectionName": "source_net_5_mst1",
      "rootConnectionName": "source_net_5"
    }
  ],
  "availableZ": [
    1
  ]
}
