{
  "capacityMeshNodeId": "cmn_35",
  "center": {
    "x": -1.1900000000000004,
    "y": 15.615000000000004
  },
  "width": 6.92,
  "height": 3.370000000000001,
  "portPoints": [
    {
      "portPointId": "ce557_pp6_z0::0",
      "x": -0.9699999999999998,
      "y": 17.300000000000004,
      "z": 0,
      "connectionName": "source_net_10_mst0",
      "rootConnectionName": "source_net_10"
    },
    {
      "portPointId": "ce559_pp3_z0::0",
      "x": 2.2699999999999996,
      "y": 15.230000000000002,
      "z": 0,
      "connectionName": "source_net_10_mst0",
      "rootConnectionName": "source_net_10"
    },
    {
      "portPointId": "ce558_pp3_z0::0",
      "x": 2.045,
      "y": 17.300000000000004,
      "z": 0,
      "connectionName": "source_net_18_mst0",
      "rootConnectionName": "source_net_18"
    },
    {
      "portPointId": "ce254_pp9_z0::0",
      "x": -1.1900000000000004,
      "y": 13.930000000000003,
      "z": 0,
      "connectionName": "source_net_18_mst0",
      "rootConnectionName": "source_net_18"
    }
  ],
  "availableZ": [
    0,
    1,
    2,
    3
  ]
}
