{
  "capacityMeshNodeId": "cmn_87",
  "center": {
    "x": 16.91,
    "y": 20.5775
  },
  "width": 5.800000000000004,
  "height": 3.004999999999999,
  "portPoints": [
    {
      "portPointId": "ce866_pp0_z0_cramped::0",
      "x": 18.910000000000004,
      "y": 19.075000000000003,
      "z": 0,
      "connectionName": "source_net_11_mst0",
      "rootConnectionName": "source_net_11"
    },
    {
      "portPointId": "ce607_pp0_z0::0",
      "x": 19.810000000000002,
      "y": 20.5775,
      "z": 0,
      "connectionName": "source_net_11_mst0",
      "rootConnectionName": "source_net_11"
    },
    {
      "portPointId": "ce671_pp0_z0::0",
      "x": 14.009999999999998,
      "y": 19.82625,
      "z": 0,
      "connectionName": "source_net_18_mst1",
      "rootConnectionName": "source_net_18"
    },
    {
      "portPointId": "ce848_pp0_z0::0",
      "x": 14.66,
      "y": 19.075000000000003,
      "z": 0,
      "connectionName": "source_net_18_mst1",
      "rootConnectionName": "source_net_18"
    },
    {
      "portPointId": "ce671_pp1_z2::2",
      "x": 14.009999999999998,
      "y": 20.5775,
      "z": 2,
      "connectionName": "source_net_27_mst0",
      "rootConnectionName": "source_net_27"
    },
    {
      "portPointId": "ce851_pp0_z0::0",
      "x": 15.66,
      "y": 19.075000000000003,
      "z": 0,
      "connectionName": "source_net_27_mst0",
      "rootConnectionName": "source_net_27"
    },
    {
      "portPointId": "ce671_pp2_z0::0",
      "x": 14.009999999999998,
      "y": 21.32875,
      "z": 0,
      "connectionName": "source_net_25_mst2",
      "rootConnectionName": "source_net_25"
    },
    {
      "portPointId": "ce854_pp0_z0::0",
      "x": 16.160000000000004,
      "y": 19.075000000000003,
      "z": 0,
      "connectionName": "source_net_25_mst2",
      "rootConnectionName": "source_net_25"
    },
    {
      "portPointId": "ce850_pp0_z0_cramped::0",
      "x": 14.91,
      "y": 19.075000000000003,
      "z": 0,
      "connectionName": "source_net_18_mst0",
      "rootConnectionName": "source_net_18"
    },
    {
      "portPointId": "ce857_pp0_z0::0",
      "x": 17.160000000000004,
      "y": 19.075000000000003,
      "z": 0,
      "connectionName": "source_net_18_mst0",
      "rootConnectionName": "source_net_18"
    },
    {
      "portPointId": "ce845_pp2_z3::3",
      "x": 15.572499999999998,
      "y": 19.075000000000003,
      "z": 3,
      "connectionName": "source_net_6_mst1",
      "rootConnectionName": "source_net_6"
    },
    {
      "portPointId": "ce849_pp0_z0::0",
      "x": 15.16,
      "y": 19.075000000000003,
      "z": 0,
      "connectionName": "source_net_6_mst1",
      "rootConnectionName": "source_net_6"
    },
    {
      "portPointId": "ce855_pp0_z0_cramped::0",
      "x": 16.410000000000004,
      "y": 19.075000000000003,
      "z": 0,
      "connectionName": "source_net_25_mst1",
      "rootConnectionName": "source_net_25"
    },
    {
      "portPointId": "ce845_pp4_z3::3",
      "x": 16.91,
      "y": 19.075000000000003,
      "z": 3,
      "connectionName": "source_net_25_mst1",
      "rootConnectionName": "source_net_25"
    },
    {
      "portPointId": "ce844_pp4_z2::2",
      "x": 16.91,
      "y": 19.075000000000003,
      "z": 2,
      "connectionName": "source_net_23_mst1",
      "rootConnectionName": "source_net_23"
    },
    {
      "portPointId": "ce856_pp0_z0::0",
      "x": 16.660000000000004,
      "y": 19.075000000000003,
      "z": 0,
      "connectionName": "source_net_23_mst1",
      "rootConnectionName": "source_net_23"
    }
  ],
  "availableZ": [
    0,
    1,
    2,
    3
  ]
}
