{
  "capacityMeshNodeId": "cmn_111",
  "center": {
    "x": 7.85,
    "y": 3.42
  },
  "width": 1.5,
  "height": 0.4500000000000006,
  "portPoints": [
    {
      "portPointId": "ce558_pp3_z3::3",
      "x": 7.85,
      "y": 3.6450000000000005,
      "z": 3,
      "connectionName": "source_net_0_mst2",
      "rootConnectionName": "source_net_0"
    },
    {
      "portPointId": "ce396_pp3_z3::3",
      "x": 7.85,
      "y": 3.1949999999999994,
      "z": 3,
      "connectionName": "source_net_0_mst2",
      "rootConnectionName": "source_net_0"
    }
  ],
  "availableZ": [
    3
  ]
}
