{
  "capacityMeshNodeId": "cmn_8",
  "center": {
    "x": -5.5005,
    "y": 10.36
  },
  "width": 11.825000000000001,
  "height": 8.830000000000002,
  "portPoints": [
    {
      "portPointId": "ce156_pp1_z0::0",
      "x": -11.413,
      "y": 12.720833333333335,
      "z": 0,
      "connectionName": "source_net_10_mst2",
      "rootConnectionName": "source_net_10"
    },
    {
      "portPointId": "ce156_pp5_z0::0",
      "x": -11.413,
      "y": 14.184166666666666,
      "z": 0,
      "connectionName": "source_net_10_mst2",
      "rootConnectionName": "source_net_10"
    },
    {
      "portPointId": "ce158_pp0_z1::1",
      "x": -11.413,
      "y": 13.065,
      "z": 1,
      "connectionName": "source_net_11_mst2",
      "rootConnectionName": "source_net_11"
    },
    {
      "portPointId": "ce155_pp4_z0::0",
      "x": -11.413,
      "y": 11.099166666666667,
      "z": 0,
      "connectionName": "source_net_11_mst2",
      "rootConnectionName": "source_net_11"
    },
    {
      "portPointId": "ce164_pp1_z0::0",
      "x": -9.313,
      "y": 14.774999999999999,
      "z": 0,
      "connectionName": "source_net_28",
      "rootConnectionName": "source_net_28"
    },
    {
      "portPointId": "ce168_pp3_z0::0",
      "x": -6.569093749999998,
      "y": 5.9449999999999985,
      "z": 0,
      "connectionName": "source_net_28",
      "rootConnectionName": "source_net_28"
    },
    {
      "portPointId": "ce168_pp3_z1::1",
      "x": -7.557062499999999,
      "y": 5.9449999999999985,
      "z": 1,
      "connectionName": "source_net_18_mst1",
      "rootConnectionName": "source_net_18"
    },
    {
      "portPointId": "ce175_pp0_z0::0",
      "x": 0.1120000000000001,
      "y": 14.775,
      "z": 0,
      "connectionName": "source_net_18_mst1",
      "rootConnectionName": "source_net_18"
    },
    {
      "portPointId": "ce170_pp1_z0::0",
      "x": -6.392166666666667,
      "y": 14.775,
      "z": 0,
      "connectionName": "source_net_21_mst1",
      "rootConnectionName": "source_net_21"
    },
    {
      "portPointId": "ce1_pp5_z0::0",
      "x": 0.41199999999999903,
      "y": 12.567499999999999,
      "z": 0,
      "connectionName": "source_net_21_mst1",
      "rootConnectionName": "source_net_21"
    },
    {
      "portPointId": "ce160_pp0_z1::1",
      "x": -11.413,
      "y": 14.334999999999999,
      "z": 1,
      "connectionName": "source_net_26_mst1",
      "rootConnectionName": "source_net_26"
    },
    {
      "portPointId": "ce164_pp4_z0::0",
      "x": -7.913,
      "y": 14.774999999999999,
      "z": 0,
      "connectionName": "source_net_26_mst1",
      "rootConnectionName": "source_net_26"
    },
    {
      "portPointId": "ce164_pp4_z1::1",
      "x": -8.263000000000002,
      "y": 14.774999999999999,
      "z": 1,
      "connectionName": "source_net_26_mst1",
      "rootConnectionName": "source_net_26"
    },
    {
      "portPointId": "ce164_pp3_z1::1",
      "x": -10.363,
      "y": 14.774999999999999,
      "z": 1,
      "connectionName": "source_net_26_mst1",
      "rootConnectionName": "source_net_26"
    },
    {
      "portPointId": "ce157_pp0_z1::1",
      "x": -11.413,
      "y": 12.43,
      "z": 1,
      "connectionName": "source_net_16_mst2",
      "rootConnectionName": "source_net_16"
    },
    {
      "portPointId": "ce168_pp1_z0::0",
      "x": -8.545031250000001,
      "y": 5.9449999999999985,
      "z": 0,
      "connectionName": "source_net_16_mst2",
      "rootConnectionName": "source_net_16"
    },
    {
      "portPointId": "ce164_pp0_z0::0",
      "x": -10.713000000000001,
      "y": 14.774999999999999,
      "z": 0,
      "connectionName": "source_net_20_mst2",
      "rootConnectionName": "source_net_20"
    },
    {
      "portPointId": "ce1_pp2_z0::0",
      "x": 0.41199999999999903,
      "y": 8.1525,
      "z": 0,
      "connectionName": "source_net_20_mst2",
      "rootConnectionName": "source_net_20"
    },
    {
      "portPointId": "ce173_pp2_z0::0",
      "x": -0.9379999999999998,
      "y": 14.775,
      "z": 0,
      "connectionName": "source_net_9",
      "rootConnectionName": "source_net_9"
    },
    {
      "portPointId": "ce1_pp5_z1::1",
      "x": 0.41199999999999903,
      "y": 10.36,
      "z": 1,
      "connectionName": "source_net_9",
      "rootConnectionName": "source_net_9"
    },
    {
      "portPointId": "ce155_pp2_z0::0",
      "x": -11.413,
      "y": 9.0375,
      "z": 0,
      "connectionName": "source_net_17_mst1",
      "rootConnectionName": "source_net_17"
    },
    {
      "portPointId": "ce170_pp4_z0::0",
      "x": -3.108833333333333,
      "y": 14.775,
      "z": 0,
      "connectionName": "source_net_17_mst1",
      "rootConnectionName": "source_net_17"
    },
    {
      "portPointId": "ce159_pp0_z1::1",
      "x": -11.413,
      "y": 13.7,
      "z": 1,
      "connectionName": "source_net_14_mst1",
      "rootConnectionName": "source_net_14"
    },
    {
      "portPointId": "ce167_pp0_z0::0",
      "x": -9.803,
      "y": 5.944999999999999,
      "z": 0,
      "connectionName": "source_net_14_mst1",
      "rootConnectionName": "source_net_14"
    },
    {
      "portPointId": "ce170_pp3_z0::0",
      "x": -4.750500000000001,
      "y": 14.775,
      "z": 0,
      "connectionName": "source_net_1_mst1",
      "rootConnectionName": "source_net_1"
    },
    {
      "portPointId": "ce171_pp4_z0::0",
      "x": -3.1886249999999987,
      "y": 5.9449999999999985,
      "z": 0,
      "connectionName": "source_net_1_mst1",
      "rootConnectionName": "source_net_1"
    },
    {
      "portPointId": "ce155_pp1_z0::0",
      "x": -11.413,
      "y": 6.975833333333332,
      "z": 0,
      "connectionName": "source_net_13_mst0",
      "rootConnectionName": "source_net_13"
    },
    {
      "portPointId": "ce165_pp0_z0::0",
      "x": -10.823,
      "y": 5.944999999999999,
      "z": 0,
      "connectionName": "source_net_13_mst0",
      "rootConnectionName": "source_net_13"
    }
  ],
  "availableZ": [
    0,
    1
  ]
}
