{
  "capacityMeshNodeId": "cmn_27",
  "center": {
    "x": -2.5399999999999996,
    "y": 8.44
  },
  "width": 1.04,
  "height": 3.120000000000001,
  "portPoints": [
    {
      "portPointId": "ce289_pp0_z1_cramped::1",
      "x": -2.853993088248899,
      "y": 6.879999999999999,
      "z": 1,
      "connectionName": "source_net_10_mst1",
      "rootConnectionName": "source_net_10"
    },
    {
      "portPointId": "ce291_pp0_z0::0",
      "x": -2.3339930882488993,
      "y": 6.879999999999999,
      "z": 0,
      "connectionName": "source_net_10_mst1",
      "rootConnectionName": "source_net_10"
    }
  ],
  "availableZ": [
    0,
    1
  ]
}
