{
  "capacityMeshNodeId": "cmn_13",
  "center": {
    "x": -3.1300000000000003,
    "y": 20.1325
  },
  "width": 6.3500000000000005,
  "height": 3.754999999999999,
  "portPoints": [
    {
      "portPointId": "ce239_pp0_z1::1",
      "x": 0.04499999999999993,
      "y": 20.07,
      "z": 1,
      "connectionName": "source_trace_18",
      "rootConnectionName": "source_trace_18"
    },
    {
      "portPointId": "ce224_pp2_z1::1",
      "x": -6.3050000000000015,
      "y": 20.927499999999995,
      "z": 1,
      "connectionName": "source_trace_18",
      "rootConnectionName": "source_trace_18"
    }
  ],
  "availableZ": [
    0,
    1
  ]
}
