{
  "capacityMeshNodeId": "cmn_0",
  "center": {
    "x": -11.15,
    "y": 1.7375000000000003
  },
  "width": 39.699999999999996,
  "height": 35.05,
  "portPoints": [
    {
      "portPointId": "ce0_pp8_z0::0",
      "x": -21.075000000000003,
      "y": -0.11249999999999982,
      "z": 0,
      "connectionName": "source_net_21_mst1",
      "rootConnectionName": "source_net_21"
    },
    {
      "portPointId": "ce12_pp1_z0::0",
      "x": -11.485000000000001,
      "y": 10.5,
      "z": 0,
      "connectionName": "source_net_21_mst1",
      "rootConnectionName": "source_net_21"
    },
    {
      "portPointId": "ce17_pp0_z0::0",
      "x": -5.220000000000001,
      "y": 10.5,
      "z": 0,
      "connectionName": "source_net_19_mst1",
      "rootConnectionName": "source_net_19"
    },
    {
      "portPointId": "ce24_pp7_z0::0",
      "x": -1.2250000000000014,
      "y": 0.3156250000000007,
      "z": 0,
      "connectionName": "source_net_19_mst1",
      "rootConnectionName": "source_net_19"
    },
    {
      "portPointId": "ce9_pp0_z0::0",
      "x": -18.099999999999994,
      "y": -7.0249999999999995,
      "z": 0,
      "connectionName": "source_net_14",
      "rootConnectionName": "source_net_14"
    },
    {
      "portPointId": "ce16_pp1_z0::0",
      "x": -6.405,
      "y": 10.5,
      "z": 0,
      "connectionName": "source_net_14",
      "rootConnectionName": "source_net_14"
    },
    {
      "portPointId": "ce17_pp1_z0::0",
      "x": -4.699999999999999,
      "y": 10.5,
      "z": 0,
      "connectionName": "source_net_12_mst1",
      "rootConnectionName": "source_net_12"
    },
    {
      "portPointId": "ce19_pp2_z0::0",
      "x": -1.653750000000001,
      "y": 10.5,
      "z": 0,
      "connectionName": "source_net_12_mst1",
      "rootConnectionName": "source_net_12"
    },
    {
      "portPointId": "ce19_pp1_z0::0",
      "x": -2.51125,
      "y": 10.5,
      "z": 0,
      "connectionName": "source_net_12_mst1",
      "rootConnectionName": "source_net_12"
    },
    {
      "portPointId": "ce24_pp11_z0::0",
      "x": -1.2250000000000014,
      "y": 8.463125,
      "z": 0,
      "connectionName": "source_net_12_mst1",
      "rootConnectionName": "source_net_12"
    },
    {
      "portPointId": "ce15_pp0_z0::0",
      "x": -7.5,
      "y": 10.5,
      "z": 0,
      "connectionName": "source_net_9_mst2",
      "rootConnectionName": "source_net_9"
    },
    {
      "portPointId": "ce24_pp9_z0::0",
      "x": -1.2250000000000014,
      "y": 4.389375000000001,
      "z": 0,
      "connectionName": "source_net_9_mst2",
      "rootConnectionName": "source_net_9"
    },
    {
      "portPointId": "ce3_pp0_z0::0",
      "x": -21.075,
      "y": 7.025,
      "z": 0,
      "connectionName": "source_net_2_mst2",
      "rootConnectionName": "source_net_2"
    },
    {
      "portPointId": "ce23_pp1_z0::0",
      "x": -1.2250000000000014,
      "y": -2.498124999999999,
      "z": 0,
      "connectionName": "source_net_2_mst2",
      "rootConnectionName": "source_net_2"
    }
  ],
  "availableZ": [
    0,
    1,
    2,
    3
  ]
}
