{
  "capacityMeshNodeId": "cmn_178",
  "center": {
    "x": -5.3,
    "y": 18
  },
  "width": 1,
  "height": 0.6999999999999993,
  "portPoints": [
    {
      "portPointId": "tiny-terminal:start-port:source_net_14_mst1",
      "x": -5.3,
      "y": 18,
      "z": 0,
      "connectionName": "source_net_14_mst1",
      "rootConnectionName": "source_net_14"
    },
    {
      "portPointId": "ce705_pp1_z0::0",
      "x": -5.025,
      "y": 17.65,
      "z": 0,
      "connectionName": "source_net_14_mst1",
      "rootConnectionName": "source_net_14"
    }
  ],
  "availableZ": [
    0
  ]
}
