{
  "capacityMeshNodeId": "cmn_151",
  "center": {
    "x": -18.7,
    "y": -10
  },
  "width": 1,
  "height": 2.599999999999998,
  "portPoints": [
    {
      "portPointId": "ce817_pp0_z0_cramped::0",
      "x": -18.2125,
      "y": -8.700000000000001,
      "z": 0,
      "connectionName": "source_net_7",
      "rootConnectionName": "source_net_7"
    },
    {
      "portPointId": "ce274_pp0_z0::0",
      "x": -18.974999999999998,
      "y": -11.3,
      "z": 0,
      "connectionName": "source_net_7",
      "rootConnectionName": "source_net_7"
    }
  ],
  "availableZ": [
    0
  ]
}
