{
  "capacityMeshNodeId": "cmn_141",
  "center": {
    "x": 16.9125,
    "y": 3
  },
  "width": 1.0249999999999986,
  "height": 1.4,
  "portPoints": [
    {
      "portPointId": "ce483_pp2_z0::0",
      "x": 16.4,
      "y": 3.158333333333333,
      "z": 0,
      "connectionName": "source_net_0_mst2",
      "rootConnectionName": "source_net_0"
    },
    {
      "portPointId": "tiny-terminal:end-port:source_net_0_mst2",
      "x": 16.9125,
      "y": 3,
      "z": 0,
      "connectionName": "source_net_0_mst2",
      "rootConnectionName": "source_net_0"
    }
  ],
  "availableZ": [
    0
  ]
}
