{
  "capacityMeshNodeId": "cmn_90",
  "center": {
    "x": -11.25,
    "y": -17.5
  },
  "width": 0.8499999999999979,
  "height": 0.9499999999999993,
  "portPoints": [
    {
      "portPointId": "ce645_pp1_z0::0",
      "x": -11.674999999999999,
      "y": -17.25,
      "z": 0,
      "connectionName": "source_net_11_mst0",
      "rootConnectionName": "source_net_11"
    },
    {
      "portPointId": "ce462_pp1_z0::0",
      "x": -11.25,
      "y": -17.025000000000002,
      "z": 0,
      "connectionName": "source_net_11_mst0",
      "rootConnectionName": "source_net_11"
    }
  ],
  "availableZ": [
    0
  ]
}
