{
  "capacityMeshNodeId": "cmn_3",
  "center": {
    "x": -0.2575000000000003,
    "y": 1.7975
  },
  "width": 12.295000000000002,
  "height": 10.455,
  "portPoints": [
    {
      "portPointId": "ce68_pp3_z1::1",
      "x": -5.0699999999999985,
      "y": -3.4299999999999997,
      "z": 1,
      "connectionName": "source_net_4_mst0",
      "rootConnectionName": "source_net_4"
    },
    {
      "portPointId": "ce71_pp0_z0::0",
      "x": -5.115,
      "y": -3.4299999999999997,
      "z": 0,
      "connectionName": "source_net_4_mst0",
      "rootConnectionName": "source_net_4"
    },
    {
      "portPointId": "ce72_pp3_z1::1",
      "x": 2.422500000000001,
      "y": -3.4299999999999997,
      "z": 1,
      "connectionName": "source_net_17",
      "rootConnectionName": "source_net_17"
    },
    {
      "portPointId": "ce73_pp1_z1::1",
      "x": -2.4750000000000005,
      "y": 7.025,
      "z": 1,
      "connectionName": "source_net_17",
      "rootConnectionName": "source_net_17"
    },
    {
      "portPointId": "ce76_pp1_z0::0",
      "x": -0.8750000000000002,
      "y": 7.025,
      "z": 0,
      "connectionName": "source_net_3_mst2",
      "rootConnectionName": "source_net_3"
    },
    {
      "portPointId": "ce79_pp0_z0::0",
      "x": 5.3675000000000015,
      "y": -3.4299999999999997,
      "z": 0,
      "connectionName": "source_net_3_mst2",
      "rootConnectionName": "source_net_3"
    },
    {
      "portPointId": "ce72_pp9_z0::0",
      "x": 8.881784197001252e-16,
      "y": -3.4299999999999997,
      "z": 0,
      "connectionName": "source_net_21_mst1",
      "rootConnectionName": "source_net_21"
    },
    {
      "portPointId": "ce77_pp6_z0::0",
      "x": 1.1949999999999998,
      "y": 7.025,
      "z": 0,
      "connectionName": "source_net_21_mst1",
      "rootConnectionName": "source_net_21"
    },
    {
      "portPointId": "ce72_pp2_z1::1",
      "x": -2.4225,
      "y": -3.4299999999999997,
      "z": 1,
      "connectionName": "source_net_8_mst1",
      "rootConnectionName": "source_net_8"
    },
    {
      "portPointId": "ce74_pp0_z0::0",
      "x": -2.8750000000000004,
      "y": 7.025,
      "z": 0,
      "connectionName": "source_net_8_mst1",
      "rootConnectionName": "source_net_8"
    }
  ],
  "availableZ": [
    0,
    1
  ]
}
